wwtp_configuration/__init__.py
wwtp_configuration/connection.py
wwtp_configuration/node.py
wwtp_configuration/parse_json.py
wwtp_configuration/tag.py
wwtp_configuration/units.py
wwtp_configuration/utils.py
wwtp_configuration/visualize.py
wwtp_configuration/data/__init__.py
wwtp_configuration/data/sample.json
wwtp_configuration/data/unit_definitions.txt
wwtp_configuration-0.3.1.dist-info/LICENSE
wwtp_configuration-0.3.1.dist-info/METADATA
wwtp_configuration-0.3.1.dist-info/WHEEL
wwtp_configuration-0.3.1.dist-info/top_level.txt
wwtp_configuration-0.3.1.dist-info/RECORD
